{
	"schemaVersion": 1,
	"id": "piechartban",
	"version": "${version}",
	"name": "Pie Chart Ban",
	"description": "This is an example description! Tell everyone what your mod is about!",
	"authors": [
		"Me!"
	],
	"contact": {
		"homepage": "https://fabricmc.net/",
		"sources": "https://github.com/FabricMC/fabric-example-mod"
	},
	"license": "MIT",
	"icon": "assets/piechartban/icon.png",
	"environment": "*",
	"entrypoints": {
		"main": [
			"com.tyz0218.PieChartBan"
		],
		"client": [
			"com.tyz0218.client.PieChartBanClient"
		]
	},
	"mixins": [
		"piechartban.mixins.json",
		{
			"config": "piechartban.client.mixins.json",
			"environment": "client"
		}
	],
	"depends": {
		"fabricloader": ">=0.19.3",
		"minecraft": "~1.21.1",
		"java": ">=21",
		"fabric-api": "*"
	}
}